ymlparse/__init__.py
ymlparse/parse_yaml.py
yamlparse-0.0.1.dist-info/LICENSE
yamlparse-0.0.1.dist-info/METADATA
yamlparse-0.0.1.dist-info/WHEEL
yamlparse-0.0.1.dist-info/entry_points.txt
yamlparse-0.0.1.dist-info/top_level.txt
yamlparse-0.0.1.dist-info/zip-safe
yamlparse-0.0.1.dist-info/RECORD
